{
  "/Converters/AreaUnit/AcresToHectare": {
    "title": "Acres To Hectare Converter — Free & Instant",
    "description": "Convert acres to hectare quickly and accurately with our free online converter."
  },
  "/Converters/AreaUnit/AcresToSquareMiles": {
    "title": "Acres To Square Miles Converter — Free & Instant",
    "description": "Convert acres to square miles quickly and accurately with our free online converter."
  },
  "/Converters/AreaUnit/HectareToAcres": {
    "title": "Hectare To Acres Converter — Free & Instant",
    "description": "Convert hectare to acres quickly and accurately with our free online converter."
  },
  "/Converters/AreaUnit/SquareFeetToSquareMeter": {
    "title": "Square Feet To Square Meter Converter — Free & Instant",
    "description": "Convert square feet to square meter quickly and accurately with our free online converter."
  },
  "/Converters/AreaUnit/SquareFeetToSquareYards": {
    "title": "Square Feet To Square Yards Converter — Free & Instant",
    "description": "Convert square feet to square yards quickly and accurately with our free online converter."
  },
  "/Converters/AreaUnit/SquareMeterToSquareFeet": {
    "title": "Square Meter To Square Feet Converter — Free & Instant",
    "description": "Convert square meter to square feet quickly and accurately with our free online converter."
  },
  "/Converters/AreaUnit/SquareMilesToAcres": {
    "title": "Square Miles To Acres Converter — Free & Instant",
    "description": "Convert square miles to acres quickly and accurately with our free online converter."
  },
  "/Converters/AreaUnit/SquareYardsToSquareFeet": {
    "title": "Square Yards To Square Feet Converter — Free & Instant",
    "description": "Convert square yards to square feet quickly and accurately with our free online converter."
  },
  "/Converters/Calculator": {
    "title": "Calculator Converter — Free & Instant",
    "description": "Convert calculator quickly and accurately with our free online converter."
  },
  "/Converters/CommonConversions/AcresToSquareFeet": {
    "title": "Acres To Square Feet Converter — Free & Instant",
    "description": "Convert acres to square feet quickly and accurately with our free online converter."
  },
  "/Converters/CommonConversions/CelsiusToFahrenheit": {
    "title": "Celsius To Fahrenheit Converter — Free & Instant",
    "description": "Convert celsius to fahrenheit quickly and accurately with our free online converter."
  },
  "/Converters/CommonConversions/CmToFeet": {
    "title": "Cm To Feet Converter — Free & Instant",
    "description": "Convert cm to feet quickly and accurately with our free online converter."
  },
  "/Converters/CommonConversions/CmToInches": {
    "title": "Cm To Inches Converter — Free & Instant",
    "description": "Convert cm to inches quickly and accurately with our free online converter."
  },
  "/Converters/CommonConversions/CupsToMl": {
    "title": "Cups To Ml Converter — Free & Instant",
    "description": "Convert cups to ml quickly and accurately with our free online converter."
  },
  "/Converters/CommonConversions/DegreesToRadians": {
    "title": "Degrees To Radians Converter — Free & Instant",
    "description": "Convert degrees to radians quickly and accurately with our free online converter."
  },
  "/Converters/CommonConversions/FahrenheitToCelsius": {
    "title": "Fahrenheit To Celsius Converter — Free & Instant",
    "description": "Convert fahrenheit to celsius quickly and accurately with our free online converter."
  },
  "/Converters/CommonConversions/FeetToCm": {
    "title": "Feet To Cm Converter — Free & Instant",
    "description": "Convert feet to cm quickly and accurately with our free online converter."
  },
  "/Converters/CommonConversions/FeetToInches": {
    "title": "Feet To Inches Converter — Free & Instant",
    "description": "Convert feet to inches quickly and accurately with our free online converter."
  },
  "/Converters/CommonConversions/FeetToMeters": {
  "title": "Feet to Meters Converter – Convert ft to m | Converthaven",
  "description": "Convert feet to meters instantly with our free Feet to Meters converter. Fast, reliable, and easy to use."
  },
  "/Converters/CommonConversions/GallonsToLiters": {
    "title": "Gallons To Liters Converter — Free & Instant",
    "description": "Convert gallons to liters quickly and accurately with our free online converter."
  },
  "/Converters/CommonConversions/HpToKw": {
    "title": "Hp To Kw Converter — Free & Instant",
    "description": "Convert hp to kw quickly and accurately with our free online converter."
  },
  "/Converters/CommonConversions/InchesToCm": {
    "title": "Inches To Cm Converter — Free & Instant",
    "description": "Convert inches to cm quickly and accurately with our free online converter."
  },
  "/Converters/CommonConversions/InchesToFeet": {
  "title": "Inches to Feet Converter – Convert Inches into Feet | Converthaven",
  "description": "Easily convert inches to feet with our free online Inches to Feet converter. Fast, accurate results with formulas and examples."
  },
  "/Converters/CommonConversions/InchesToMm": {
  "title": "Inches to Millimeters Converter – Convert in to mm | Converthaven",
  "description": "Convert inches to millimeters instantly with our free Inches to mm converter. Accurate results, simple formula, and examples."
  },
  "/Converters/CommonConversions/KmToMiles": {
    "title": "Km To Miles Converter — Free & Instant",
    "description": "Convert km to miles quickly and accurately with our free online converter."
  },
  "/Converters/CommonConversions/KphToMph": {
    "title": "Kph To Mph Converter — Free & Instant",
    "description": "Convert kph to mph quickly and accurately with our free online converter."
  },
  "/Converters/CommonConversions/KwToHp": {
    "title": "Kw To Hp Converter — Free & Instant",
    "description": "Convert kw to hp quickly and accurately with our free online converter."
  },
  "/Converters/CommonConversions/LitersToGallons": {
    "title": "Liters To Gallons Converter — Free & Instant",
    "description": "Convert liters to gallons quickly and accurately with our free online converter."
  },
  "/Converters/CommonConversions/MetersToFeet": {
    "title": "Meters To Feet Converter — Free & Instant",
    "description": "Convert meters to feet quickly and accurately with our free online converter."
  },
  "/Converters/CommonConversions/MetersToYards": {
  "title": "Meters to Yards Converter – Convert m to yd | Converthaven",
  "description": "Convert meters to yards quickly using our free online converter. Accurate results for construction and measurement needs."
  },
  "/Converters/CommonConversions/MilesToKm": {
    "title": "Miles To Km Converter — Free & Instant",
    "description": "Convert miles to km quickly and accurately with our free online converter."
  },
  "/Converters/CommonConversions/MlToCups": {
    "title": "Ml To Cups Converter — Free & Instant",
    "description": "Convert ml to cups quickly and accurately with our free online converter."
  },
    "/Converters/CommonConversions/MmToInches": {
    "title": "mm To Inches Converter — Free & Instant",
    "description": "Convert mm to inches quickly and accurately with our free online converter."
  },
  "/Converters/CommonConversions/MphToKph": {
    "title": "MPH to KPH Converter – Convert Miles per Hour to Kilometers | Converthaven",
    "description": "Convert mph to kph quickly and accurately with our free online converter."
  },
  "/Converters/CommonConversions/RadiansToDegrees": {
    "title": "Radians To Degrees Converter — Free & Instant",
    "description": "Convert radians to degrees quickly and accurately with our free online converter."
  },
  "/Converters/CommonConversions/SquareFeetToAcres": {
  "title": "Square Feet to Acres Converter – Convert sq ft to acres | Converthaven",
  "description": "Easily convert square feet to acres with our free Square Feet to Acres converter. Ideal for land and area calculations."
  },
  "/Converters/CommonConversions/YardsToMeters": {
  "title": "Yards to Meters Converter – Convert yd to m | Converthaven",
  "description": "Convert yards to meters effortlessly with our free Yards to Meters converter. Accurate calculations with clear explanations."
  },
  "/Converters/CommonConverters/AngleConverter": {
    "title": "Angle Converter Converter — Free & Instant",
    "description": "Convert angle converter quickly and accurately with our free online converter."
  },
  "/Converters/CommonConverters/AreaConverter": {
    "title": "Area Converter Converter — Free & Instant",
    "description": "Convert area converter quickly and accurately with our free online converter."
  },
  "/Converters/CommonConverters/CaseConverter": {
    "title": "Case Converter Converter — Free & Instant",
    "description": "Convert case converter quickly and accurately with our free online converter."
  },
  "/Converters/CommonConverters/DataStorageConverter": {
    "title": "Data Storage Converter Converter — Free & Instant",
    "description": "Convert data storage converter quickly and accurately with our free online converter."
  },
  "/Converters/CommonConverters/EnergyConverter": {
    "title": "Energy Converter Converter — Free & Instant",
    "description": "Convert energy converter quickly and accurately with our free online converter."
  },
  "/Converters/CommonConverters/ForceConverter": {
    "title": "Force Converter Converter — Free & Instant",
    "description": "Convert force converter quickly and accurately with our free online converter."
  },
  "/Converters/CommonConverters/FuelConsumptionConverter": {
    "title": "Fuel Consumption Converter Converter — Free & Instant",
    "description": "Convert fuel consumption converter quickly and accurately with our free online converter."
  },
  "/Converters/CommonConverters/LengthConverter": {
    "title": "Length Converter Converter — Free & Instant",
    "description": "Convert length converter quickly and accurately with our free online converter."
  },
  "/Converters/CommonConverters/NumbersConverter": {
    "title": "Numbers Converter Converter — Free & Instant",
    "description": "Convert numbers converter quickly and accurately with our free online converter."
  },
  "/Converters/CommonConverters/PowerConverter": {
    "title": "Power Converter Converter — Free & Instant",
    "description": "Convert power converter quickly and accurately with our free online converter."
  },
  "/Converters/CommonConverters/PressureConverter": {
    "title": "Pressure Converter Converter — Free & Instant",
    "description": "Convert pressure converter quickly and accurately with our free online converter."
  },
  "/Converters/CommonConverters/SpeedConverter": {
    "title": "Speed Converter Converter — Free & Instant",
    "description": "Convert speed converter quickly and accurately with our free online converter."
  },
  "/Converters/CommonConverters/TemperatureConverter": {
    "title": "Temperature Converter Converter — Free & Instant",
    "description": "Convert temperature converter quickly and accurately with our free online converter."
  },
  "/Converters/CommonConverters/TimeConverter": {
    "title": "Time Converter Converter — Free & Instant",
    "description": "Convert time converter quickly and accurately with our free online converter."
  },
  "/Converters/CommonConverters/VolumeConverter": {
    "title": "Volume Converter Converter — Free & Instant",
    "description": "Convert volume converter quickly and accurately with our free online converter."
  },
  "/Converters/CommonConverters/VolumeDryConverter": {
    "title": "Volume Dry Converter Converter — Free & Instant",
    "description": "Convert volume dry converter quickly and accurately with our free online converter."
  },
  "/Converters/CommonConverters/WeightAndMassConverter": {
    "title": "Weight And Mass Converter Converter — Free & Instant",
    "description": "Convert weight and mass converter quickly and accurately with our free online converter."
  },
  "/Converters/DataStorageUnits/GBToKB": {
    "title": "GBTo KB Converter — Free & Instant",
    "description": "Convert gbto kb quickly and accurately with our free online converter."
  },
  "/Converters/DataStorageUnits/GBToMB": {
    "title": "GBTo MB Converter — Free & Instant",
    "description": "Convert gbto mb quickly and accurately with our free online converter."
  },
  "/Converters/DataStorageUnits/KBToGB": {
    "title": "KBTo GB Converter — Free & Instant",
    "description": "Convert kbto gb quickly and accurately with our free online converter."
  },
  "/Converters/DataStorageUnits/KBToMB": {
    "title": "KBTo MB Converter — Free & Instant",
    "description": "Convert kbto mb quickly and accurately with our free online converter."
  },
  "/Converters/DataStorageUnits/MBToGB": {
    "title": "MBTo GB Converter — Free & Instant",
    "description": "Convert mbto gb quickly and accurately with our free online converter."
  },
  "/Converters/DataStorageUnits/MBToKB": {
    "title": "MBTo KB Converter — Free & Instant",
    "description": "Convert mbto kb quickly and accurately with our free online converter."
  },
  "/Converters/ElectricityConverters/ChargeConverter": {
    "title": "Charge Converter Converter — Free & Instant",
    "description": "Convert charge converter quickly and accurately with our free online converter."
  },
  "/Converters/ElectricityConverters/CurrentConverter": {
    "title": "Current Converter Converter — Free & Instant",
    "description": "Convert current converter quickly and accurately with our free online converter."
  },
  "/Converters/ElectricityConverters/ElectricConductanceConverter": {
    "title": "Electric Conductance Converter Converter — Free & Instant",
    "description": "Convert electric conductance converter quickly and accurately with our free online converter."
  },
  "/Converters/ElectricityConverters/ElectricConductivityConverter": {
    "title": "Electric Conductivity Converter Converter — Free & Instant",
    "description": "Convert electric conductivity converter quickly and accurately with our free online converter."
  },
  "/Converters/ElectricityConverters/ElectricFieldStrengthConverter": {
    "title": "Electric Field Strength Converter Converter — Free & Instant",
    "description": "Convert electric field strength converter quickly and accurately with our free online converter."
  },
  "/Converters/ElectricityConverters/ElectricPotentialConverter": {
    "title": "Electric Potential Converter Converter — Free & Instant",
    "description": "Convert electric potential converter quickly and accurately with our free online converter."
  },
  "/Converters/ElectricityConverters/ElectricResistanceConverter": {
    "title": "Electric Resistance Converter Converter — Free & Instant",
    "description": "Convert electric resistance converter quickly and accurately with our free online converter."
  },
  "/Converters/ElectricityConverters/ElectricResistivityConverter": {
    "title": "Electric Resistivity Converter Converter — Free & Instant",
    "description": "Convert electric resistivity converter quickly and accurately with our free online converter."
  },
  "/Converters/ElectricityConverters/ElectrostaticCapacitance": {
    "title": "Electrostatic Capacitance Converter — Free & Instant",
    "description": "Convert electrostatic capacitance quickly and accurately with our free online converter."
  },
  "/Converters/ElectricityConverters/InductanceConverter": {
    "title": "Inductance Converter Converter — Free & Instant",
    "description": "Convert inductance converter quickly and accurately with our free online converter."
  },
  "/Converters/ElectricityConverters/LinearChargeDensityConverter": {
    "title": "Linear Charge Density Converter Converter — Free & Instant",
    "description": "Convert linear charge density converter quickly and accurately with our free online converter."
  },
  "/Converters/ElectricityConverters/LinearCurrentDensityConverter": {
    "title": "Linear Current Density Converter Converter — Free & Instant",
    "description": "Convert linear current density converter quickly and accurately with our free online converter."
  },
  "/Converters/ElectricityConverters/SurfaceChargeDensityConverter": {
    "title": "Surface Charge Density Converter Converter — Free & Instant",
    "description": "Convert surface charge density converter quickly and accurately with our free online converter."
  },
  "/Converters/ElectricityConverters/SurfaceCurrentDensityConverter": {
    "title": "Surface Current Density Converter Converter — Free & Instant",
    "description": "Convert surface current density converter quickly and accurately with our free online converter."
  },
  "/Converters/ElectricityConverters/VolumeChargeDensityConverter": {
    "title": "Volume Charge Density Converter Converter — Free & Instant",
    "description": "Convert volume charge density converter quickly and accurately with our free online converter."
  },
  "/Converters/EnergyUnits/CalToJ": {
    "title": "Cal To J Converter — Free & Instant",
    "description": "Convert cal to j quickly and accurately with our free online converter."
  },
  "/Converters/EnergyUnits/CalToKcal": {
    "title": "Cal To Kcal Converter — Free & Instant",
    "description": "Convert cal to kcal quickly and accurately with our free online converter."
  },
  "/Converters/EnergyUnits/FtLbToNm": {
    "title": "Ft Lb To Nm Converter — Free & Instant",
    "description": "Convert ft lb to nm quickly and accurately with our free online converter."
  },
  "/Converters/EnergyUnits/JToCal": {
    "title": "JTo Cal Converter — Free & Instant",
    "description": "Convert jto cal quickly and accurately with our free online converter."
  },
  "/Converters/EnergyUnits/JToKJ": {
    "title": "JTo KJ Converter — Free & Instant",
    "description": "Convert jto kj quickly and accurately with our free online converter."
  },
  "/Converters/EnergyUnits/KcalToCal": {
    "title": "Kcal To Cal Converter — Free & Instant",
    "description": "Convert kcal to cal quickly and accurately with our free online converter."
  },
  "/Converters/EnergyUnits/KcalToKJ": {
    "title": "Kcal To KJ Converter — Free & Instant",
    "description": "Convert kcal to kj quickly and accurately with our free online converter."
  },
  "/Converters/EnergyUnits/KJToJ": {
    "title": "KJTo J Converter — Free & Instant",
    "description": "Convert kjto j quickly and accurately with our free online converter."
  },
  "/Converters/EnergyUnits/KJToKcal": {
    "title": "KJTo Kcal Converter — Free & Instant",
    "description": "Convert kjto kcal quickly and accurately with our free online converter."
  },
  "/Converters/EnergyUnits/NmToFtLb": {
    "title": "Nm To Ft Lb Converter — Free & Instant",
    "description": "Convert nm to ft lb quickly and accurately with our free online converter."
  },
  "/Converters/EngineeringConverters/AccelerationAngularConverter": {
    "title": "Acceleration Angular Converter Converter — Free & Instant",
    "description": "Convert acceleration angular converter quickly and accurately with our free online converter."
  },
  "/Converters/EngineeringConverters/AccelerationConverter": {
    "title": "Acceleration Converter Converter — Free & Instant",
    "description": "Convert acceleration converter quickly and accurately with our free online converter."
  },
  "/Converters/EngineeringConverters/DensityConverter": {
    "title": "Density Converter Converter — Free & Instant",
    "description": "Convert density converter quickly and accurately with our free online converter."
  },
  "/Converters/EngineeringConverters/MomentOfForceConverter": {
    "title": "Moment Of Force Converter Converter — Free & Instant",
    "description": "Convert moment of force converter quickly and accurately with our free online converter."
  },
  "/Converters/EngineeringConverters/MomentOfInertiaConverter": {
    "title": "Moment Of Inertia Converter Converter — Free & Instant",
    "description": "Convert moment of inertia converter quickly and accurately with our free online converter."
  },
  "/Converters/EngineeringConverters/SpecificVolumeConverter": {
    "title": "Specific Volume Converter Converter — Free & Instant",
    "description": "Convert specific volume converter quickly and accurately with our free online converter."
  },
  "/Converters/EngineeringConverters/TorqueConverter": {
    "title": "Torque Converter Converter — Free & Instant",
    "description": "Convert torque converter quickly and accurately with our free online converter."
  },
  "/Converters/EngineeringConverters/VelocityAngularConverter": {
    "title": "Velocity Angular Converter Converter — Free & Instant",
    "description": "Convert velocity angular converter quickly and accurately with our free online converter."
  },
  "/Converters/FluidsConverters/ConcentrationMolarConverter": {
    "title": "Concentration Molar Converter Converter — Free & Instant",
    "description": "Convert concentration molar converter quickly and accurately with our free online converter."
  },
  "/Converters/FluidsConverters/ConcentrationSolutionConverter": {
    "title": "Concentration Solution Converter Converter — Free & Instant",
    "description": "Convert concentration solution converter quickly and accurately with our free online converter."
  },
  "/Converters/FluidsConverters/FlowConverter": {
    "title": "Flow Converter Converter — Free & Instant",
    "description": "Convert flow converter quickly and accurately with our free online converter."
  },
  "/Converters/FluidsConverters/FlowMassConverter": {
    "title": "Flow Mass Converter Converter — Free & Instant",
    "description": "Convert flow mass converter quickly and accurately with our free online converter."
  },
  "/Converters/FluidsConverters/FlowMolarConverter": {
    "title": "Flow Molar Converter Converter — Free & Instant",
    "description": "Convert flow molar converter quickly and accurately with our free online converter."
  },
  "/Converters/FluidsConverters/MassFluxDensityConverter": {
    "title": "Mass Flux Density Converter Converter — Free & Instant",
    "description": "Convert mass flux density converter quickly and accurately with our free online converter."
  },
  "/Converters/FluidsConverters/PermeabilityConverter": {
    "title": "Permeability Converter Converter — Free & Instant",
    "description": "Convert permeability converter quickly and accurately with our free online converter."
  },
  "/Converters/FluidsConverters/SurfaceTensionConverter": {
    "title": "Surface Tension Converter Converter — Free & Instant",
    "description": "Convert surface tension converter quickly and accurately with our free online converter."
  },
  "/Converters/FluidsConverters/ViscosityDynamicConverter": {
    "title": "Viscosity Dynamic Converter Converter — Free & Instant",
    "description": "Convert viscosity dynamic converter quickly and accurately with our free online converter."
  },
  "/Converters/FluidsConverters/ViscosityKinematicConverter": {
    "title": "Viscosity Kinematic Converter Converter — Free & Instant",
    "description": "Convert viscosity kinematic converter quickly and accurately with our free online converter."
  },
  "/Converters/Force/KgToNewtons": {
    "title": "kg To Newtons Converter — Free & Instant",
    "description": "Convert kg to newtons quickly and accurately with our free online converter."
  },
  "/Converters/Force/LbsToNewtons": {
    "title": "Lbs To Newtons Converter — Free & Instant",
    "description": "Convert lbs to newtons quickly and accurately with our free online converter."
  },
  "/Converters/Force/NewtonsToKg": {
    "title": "Newtons To kg Converter — Free & Instant",
    "description": "Convert newtons to kg quickly and accurately with our free online converter."
  },
  "/Converters/Force/NewtonsToLbs": {
    "title": "Newtons To Lbs Converter — Free & Instant",
    "description": "Convert newtons to lbs quickly and accurately with our free online converter."
  },
  "/Converters/HeatConverters/FuelEfficiencyMassConverter": {
    "title": "Fuel Efficiency Mass Converter Converter — Free & Instant",
    "description": "Convert fuel efficiency mass converter quickly and accurately with our free online converter."
  },
  "/Converters/HeatConverters/FuelEfficiencyVolumeConverter": {
    "title": "Fuel Efficiency Volume Converter Converter — Free & Instant",
    "description": "Convert fuel efficiency volume converter quickly and accurately with our free online converter."
  },
  "/Converters/HeatConverters/HeatDensityConverter": {
    "title": "Heat Density Converter Converter — Free & Instant",
    "description": "Convert heat density converter quickly and accurately with our free online converter."
  },
  "/Converters/HeatConverters/HeatFluxDensityConverter": {
    "title": "Heat Flux Density Converter Converter — Free & Instant",
    "description": "Convert heat flux density converter quickly and accurately with our free online converter."
  },
  "/Converters/HeatConverters/HeatTransferCoefficientConverter": {
    "title": "Heat Transfer Coefficient Converter Converter — Free & Instant",
    "description": "Convert heat transfer coefficient converter quickly and accurately with our free online converter."
  },
  "/Converters/HeatConverters/SpecificHeatCapacityConverter": {
    "title": "Specific Heat Capacity Converter Converter — Free & Instant",
    "description": "Convert specific heat capacity converter quickly and accurately with our free online converter."
  },
  "/Converters/HeatConverters/TemperatureIntervalConverter": {
    "title": "Temperature Interval Converter Converter — Free & Instant",
    "description": "Convert temperature interval converter quickly and accurately with our free online converter."
  },
  "/Converters/HeatConverters/ThermalConductivityConverter": {
    "title": "Thermal Conductivity Converter Converter — Free & Instant",
    "description": "Convert thermal conductivity converter quickly and accurately with our free online converter."
  },
  "/Converters/HeatConverters/ThermalExpansionConverter": {
    "title": "Thermal Expansion Converter Converter — Free & Instant",
    "description": "Convert thermal expansion converter quickly and accurately with our free online converter."
  },
  "/Converters/HeatConverters/ThermalResistanceConverter": {
    "title": "Thermal Resistance Converter Converter — Free & Instant",
    "description": "Convert thermal resistance converter quickly and accurately with our free online converter."
  },
  "/Converters/LengthUnits/CmToKilometers": {
    "title": "Cm To Kilometers Converter — Free & Instant",
    "description": "Convert cm to kilometers quickly and accurately with our free online converter."
  },
  "/Converters/LengthUnits/CmToMeters": {
    "title": "Cm To Meters Converter — Free & Instant",
    "description": "Convert cm to meters quickly and accurately with our free online converter."
  },
  "/Converters/LengthUnits/CmToMillimeters": {
    "title": "Cm To Millimeters Converter — Free & Instant",
    "description": "Convert cm to millimeters quickly and accurately with our free online converter."
  },
  "/Converters/LengthUnits/FeetToMiles": {
    "title": "Feet To Miles Converter — Free & Instant",
    "description": "Convert feet to miles quickly and accurately with our free online converter."
  },
  "/Converters/LengthUnits/FeetToMillimeters": {
    "title": "Feet To Millimeters Converter — Free & Instant",
    "description": "Convert feet to millimeters quickly and accurately with our free online converter."
  },
  "/Converters/LengthUnits/FeetToYards": {
    "title": "Feet To Yards Converter — Free & Instant",
    "description": "Convert feet to yards quickly and accurately with our free online converter."
  },
  "/Converters/CommonConversions/InchesToMeters": {
  "title": "Inches to Meters Converter – Convert Inches into Meters | Converthaven",
  "description": "Quickly convert inches to meters using our free online Inches to Meters converter. Fast, accurate, and easy to use."
  },
  "/Converters/LengthUnits/InchesToYards": {
    "title": "Inches To Yards Converter — Free & Instant",
    "description": "Convert inches to yards quickly and accurately with our free online converter."
  },
  "/Converters/LengthUnits/KilometersToCm": {
    "title": "Kilometers To Cm Converter — Free & Instant",
    "description": "Convert kilometers to cm quickly and accurately with our free online converter."
  },
  "/Converters/LengthUnits/KilometersToMeters": {
    "title": "Kilometers To Meters Converter — Free & Instant",
    "description": "Convert kilometers to meters quickly and accurately with our free online converter."
  },
  "/Converters/LengthUnits/MetersToCm": {
    "title": "Meters To Cm Converter — Free & Instant",
    "description": "Convert meters to cm quickly and accurately with our free online converter."
  },
  "/Converters/LengthUnits/MetersToInches": {
    "title": "Meters To Inches Converter — Free & Instant",
    "description": "Convert meters to inches quickly and accurately with our free online converter."
  },
  "/Converters/LengthUnits/MetersToKilometers": {
    "title": "Meters To Kilometers Converter — Free & Instant",
    "description": "Convert meters to kilometers quickly and accurately with our free online converter."
  },
  "/Converters/LengthUnits/MetersToMiles": {
    "title": "Meters To Miles Converter — Free & Instant",
    "description": "Convert meters to miles quickly and accurately with our free online converter."
  },
  "/Converters/LengthUnits/MetersToMillimeters": {
    "title": "Meters To Millimeters Converter — Free & Instant",
    "description": "Convert meters to millimeters quickly and accurately with our free online converter."
  },
  "/Converters/LengthUnits/MilesToFeet": {
    "title": "Miles To Feet Converter — Free & Instant",
    "description": "Convert miles to feet quickly and accurately with our free online converter."
  },
  "/Converters/LengthUnits/MilesToMeters": {
    "title": "Miles To Meters Converter — Free & Instant",
    "description": "Convert miles to meters quickly and accurately with our free online converter."
  },
  "/Converters/LengthUnits/MilesToYards": {
    "title": "Miles To Yards Converter — Free & Instant",
    "description": "Convert miles to yards quickly and accurately with our free online converter."
  },
  "/Converters/LengthUnits/MillimetersToCm": {
    "title": "Millimeters To Cm Converter — Free & Instant",
    "description": "Convert millimeters to cm quickly and accurately with our free online converter."
  },
  "/Converters/LengthUnits/MillimetersToFeet": {
    "title": "Millimeters To Feet Converter — Free & Instant",
    "description": "Convert millimeters to feet quickly and accurately with our free online converter."
  },
  "/Converters/LengthUnits/MillimetersToMeters": {
    "title": "Millimeters To Meters Converter — Free & Instant",
    "description": "Convert millimeters to meters quickly and accurately with our free online converter."
  },
  "/Converters/LengthUnits/YardsToFeet": {
    "title": "Yards To Feet Converter — Free & Instant",
    "description": "Convert yards to feet quickly and accurately with our free online converter."
  },
  "/Converters/LengthUnits/YardsToInches": {
    "title": "Yards To Inches Converter — Free & Instant",
    "description": "Convert yards to inches quickly and accurately with our free online converter."
  },
  "/Converters/LengthUnits/YardsToMiles": {
    "title": "Yards To Miles Converter — Free & Instant",
    "description": "Convert yards to miles quickly and accurately with our free online converter."
  },
  "/Converters/LightConverters/DigitalImageResolutionConverter": {
    "title": "Digital Image Resolution Converter Converter — Free & Instant",
    "description": "Convert digital image resolution converter quickly and accurately with our free online converter."
  },
  "/Converters/LightConverters/FrequencyWavelengthConverter": {
    "title": "Frequency Wavelength Converter Converter — Free & Instant",
    "description": "Convert frequency wavelength converter quickly and accurately with our free online converter."
  },
  "/Converters/LightConverters/IlluminationConverter": {
    "title": "Illumination Converter Converter — Free & Instant",
    "description": "Convert illumination converter quickly and accurately with our free online converter."
  },
  "/Converters/LightConverters/LuminanceConverter": {
    "title": "Luminance Converter Converter — Free & Instant",
    "description": "Convert luminance converter quickly and accurately with our free online converter."
  },
  "/Converters/LightConverters/LuminousIntensityConverter": {
    "title": "Luminous Intensity Converter Converter — Free & Instant",
    "description": "Convert luminous intensity converter quickly and accurately with our free online converter."
  },
  "/Converters/linkedConversions/AcresToOthers": {
    "title": "Acres To Others Converter — Free & Instant",
    "description": "Convert acres to others quickly and accurately with our free online converter."
  },
  "/Converters/linkedConversions/BarToOthers": {
    "title": "Bar To Others Converter — Free & Instant",
    "description": "Convert bar to others quickly and accurately with our free online converter."
  },
  "/Converters/linkedConversions/BinaryToOthers": {
    "title": "Binary To Others Converter — Free & Instant",
    "description": "Convert binary to others quickly and accurately with our free online converter."
  },
  "/Converters/linkedConversions/BtuToOThers": {
    "title": "Btu To OThers Converter — Free & Instant",
    "description": "Convert btu to others quickly and accurately with our free online converter."
  },
  "/Converters/linkedConversions/CalToOthers": {
    "title": "Cal To Others Converter — Free & Instant",
    "description": "Convert cal to others quickly and accurately with our free online converter."
  },
  "/Converters/linkedConversions/CelsiusToOthers": {
    "title": "Celsius To Others Converter — Free & Instant",
    "description": "Convert celsius to others quickly and accurately with our free online converter."
  },
  "/Converters/linkedConversions/CmToOthers": {
    "title": "Cm To Others Converter — Free & Instant",
    "description": "Convert cm to others quickly and accurately with our free online converter."
  },
  "/Converters/linkedConversions/CubicCmToOther": {
    "title": "Cubic Cm To Other Converter — Free & Instant",
    "description": "Convert cubic cm to other quickly and accurately with our free online converter."
  },
  "/Converters/linkedConversions/CubicFootToOthers": {
    "title": "Cubic Foot To Others Converter — Free & Instant",
    "description": "Convert cubic foot to others quickly and accurately with our free online converter."
  },
  "/Converters/linkedConversions/CubicInchesToOthers": {
    "title": "Cubic Inches To Others Converter — Free & Instant",
    "description": "Convert cubic inches to others quickly and accurately with our free online converter."
  },
  "/Converters/linkedConversions/CubicYardsToOthers": {
    "title": "Cubic Yards To Others Converter — Free & Instant",
    "description": "Convert cubic yards to others quickly and accurately with our free online converter."
  },
  "/Converters/linkedConversions/CupsToOthers": {
    "title": "Cups To Others Converter — Free & Instant",
    "description": "Convert cups to others quickly and accurately with our free online converter."
  },
  "/Converters/linkedConversions/DayToOthers": {
    "title": "Day To Others Converter — Free & Instant",
    "description": "Convert day to others quickly and accurately with our free online converter."
  },
  "/Converters/linkedConversions/DecimalToOthers": {
    "title": "Decimal To Others Converter — Free & Instant",
    "description": "Convert decimal to others quickly and accurately with our free online converter."
  },
  "/Converters/linkedConversions/DegreeToOThers": {
    "title": "Degree To OThers Converter — Free & Instant",
    "description": "Convert degree to others quickly and accurately with our free online converter."
  },
  "/Converters/linkedConversions/FarenheitToOthers": {
    "title": "Farenheit To Others Converter — Free & Instant",
    "description": "Convert farenheit to others quickly and accurately with our free online converter."
  },
  "/Converters/linkedConversions/FeetPerSecondToOthers": {
    "title": "Feet Per Second To Others Converter — Free & Instant",
    "description": "Convert feet per second to others quickly and accurately with our free online converter."
  },
  "/Converters/linkedConversions/FluidOunceToOthers": {
    "title": "Fluid Ounce To Others Converter — Free & Instant",
    "description": "Convert fluid ounce to others quickly and accurately with our free online converter."
  },
  "/Converters/linkedConversions/FootPoundToOthers": {
    "title": "Foot Pound To Others Converter — Free & Instant",
    "description": "Convert foot pound to others quickly and accurately with our free online converter."
  },
  "/Converters/linkedConversions/FootToOthers": {
    "title": "Foot To Others Converter — Free & Instant",
    "description": "Convert foot to others quickly and accurately with our free online converter."
  },
  "/Converters/linkedConversions/GallonToOthers": {
    "title": "Gallon To Others Converter — Free & Instant",
    "description": "Convert gallon to others quickly and accurately with our free online converter."
  },
  "/Converters/linkedConversions/GigaByteToOthers": {
    "title": "Giga Byte To Others Converter — Free & Instant",
    "description": "Convert giga byte to others quickly and accurately with our free online converter."
  },
  "/Converters/linkedConversions/GmToOthers": {
    "title": "Gm To Others Converter — Free & Instant",
    "description": "Convert gm to others quickly and accurately with our free online converter."
  },
  "/Converters/linkedConversions/HectareToOthers": {
    "title": "Hectare To Others Converter — Free & Instant",
    "description": "Convert hectare to others quickly and accurately with our free online converter."
  },
  "/Converters/linkedConversions/HexaDecimalToOthers": {
    "title": "Hexa Decimal To Others Converter — Free & Instant",
    "description": "Convert hexa decimal to others quickly and accurately with our free online converter."
  },
  "/Converters/linkedConversions/HorsePowerToOthers": {
    "title": "Horse Power To Others Converter — Free & Instant",
    "description": "Convert horse power to others quickly and accurately with our free online converter."
  },
  "/Converters/linkedConversions/HourToOthers": {
    "title": "Hour To Others Converter — Free & Instant",
    "description": "Convert hour to others quickly and accurately with our free online converter."
  },
  "/Converters/linkedConversions/InchToOthers": {
    "title": "Inch To Others Converter — Free & Instant",
    "description": "Convert inch to others quickly and accurately with our free online converter."
  },
  "/Converters/linkedConversions/JToOthers": {
    "title": "JTo Others Converter — Free & Instant",
    "description": "Convert jto others quickly and accurately with our free online converter."
  },
  "/Converters/linkedConversions/KelvinToOthers": {
    "title": "Kelvin To Others Converter — Free & Instant",
    "description": "Convert kelvin to others quickly and accurately with our free online converter."
  },
  "/Converters/linkedConversions/KgToOthers": {
    "title": "kg To Others Converter — Free & Instant",
    "description": "Convert kg to others quickly and accurately with our free online converter."
  },
  "/Converters/linkedConversions/KiloByteToOthers": {
    "title": "Kilo Byte To Others Converter — Free & Instant",
    "description": "Convert kilo byte to others quickly and accurately with our free online converter."
  },
  "/Converters/linkedConversions/KiloCalorie(th)ToOthers": {
    "title": "Kilo Calorie(th)To Others Converter — Free & Instant",
    "description": "Convert kilo calorie(th)to others quickly and accurately with our free online converter."
  },
  "/Converters/linkedConversions/KilogramForceToOthers": {
    "title": "Kilogram Force To Others Converter — Free & Instant",
    "description": "Convert kilogram force to others quickly and accurately with our free online converter."
  },
  "/Converters/linkedConversions/KiloJouleToOthers": {
    "title": "Kilo Joule To Others Converter — Free & Instant",
    "description": "Convert kilo joule to others quickly and accurately with our free online converter."
  },
  "/Converters/linkedConversions/KiloMetersToOthers": {
    "title": "Kilo Meters To Others Converter — Free & Instant",
    "description": "Convert kilo meters to others quickly and accurately with our free online converter."
  },
  "/Converters/linkedConversions/KiloPascalToOthers": {
    "title": "Kilo Pascal To Others Converter — Free & Instant",
    "description": "Convert kilo pascal to others quickly and accurately with our free online converter."
  },
  "/Converters/linkedConversions/KilowattToOthers": {
    "title": "Kilowatt To Others Converter — Free & Instant",
    "description": "Convert kilowatt to others quickly and accurately with our free online converter."
  },
  "/Converters/linkedConversions/KmToOthers": {
    "title": "Km To Others Converter — Free & Instant",
    "description": "Convert km to others quickly and accurately with our free online converter."
  },
  "/Converters/linkedConversions/LitersToOthers": {
    "title": "Liters To Others Converter — Free & Instant",
    "description": "Convert liters to others quickly and accurately with our free online converter."
  },
  "/Converters/linkedConversions/MegaByteToOthers": {
    "title": "Mega Byte To Others Converter — Free & Instant",
    "description": "Convert mega byte to others quickly and accurately with our free online converter."
  },
  "/Converters/linkedConversions/MetersPerSecondToOThers": {
    "title": "Meters Per Second To OThers Converter — Free & Instant",
    "description": "Convert meters per second to others quickly and accurately with our free online converter."
  },
  "/Converters/linkedConversions/MetersToOthers": {
    "title": "Meters To Others Converter — Free & Instant",
    "description": "Convert meters to others quickly and accurately with our free online converter."
  },
  "/Converters/linkedConversions/MgToOthers": {
    "title": "Mg To Others Converter — Free & Instant",
    "description": "Convert mg to others quickly and accurately with our free online converter."
  },
  "/Converters/linkedConversions/MilesPerHoursToOthers": {
    "title": "Miles Per Hours To Others Converter — Free & Instant",
    "description": "Convert miles per hours to others quickly and accurately with our free online converter."
  },
  "/Converters/linkedConversions/MileToOthers": {
    "title": "Mile To Others Converter — Free & Instant",
    "description": "Convert mile to others quickly and accurately with our free online converter."
  },
  "/Converters/linkedConversions/MillieSecondToOthers": {
    "title": "Millie Second To Others Converter — Free & Instant",
    "description": "Convert millie second to others quickly and accurately with our free online converter."
  },
  "/Converters/linkedConversions/MinutesToOthers": {
    "title": "Minutes To Others Converter — Free & Instant",
    "description": "Convert minutes to others quickly and accurately with our free online converter."
  },
  "/Converters/linkedConversions/MlToOthers": {
    "title": "Ml To Others Converter — Free & Instant",
    "description": "Convert ml to others quickly and accurately with our free online converter."
  },
  "/Converters/linkedConversions/MmToOthers": {
    "title": "mm To Others Converter — Free & Instant",
    "description": "Convert mm to others quickly and accurately with our free online converter."
  },
  "/Converters/linkedConversions/MonthsToOthers": {
    "title": "Months To Others Converter — Free & Instant",
    "description": "Convert months to others quickly and accurately with our free online converter."
  },
  "/Converters/linkedConversions/NewtonToOthers": {
    "title": "Newton To Others Converter — Free & Instant",
    "description": "Convert newton to others quickly and accurately with our free online converter."
  },
  "/Converters/linkedConversions/OunceToOthers": {
    "title": "Ounce To Others Converter — Free & Instant",
    "description": "Convert ounce to others quickly and accurately with our free online converter."
  },
  "/Converters/linkedConversions/PintToOthers": {
    "title": "Pint To Others Converter — Free & Instant",
    "description": "Convert pint to others quickly and accurately with our free online converter."
  },
  "/Converters/linkedConversions/PoundToOthers": {
    "title": "Pound To Others Converter — Free & Instant",
    "description": "Convert pound to others quickly and accurately with our free online converter."
  },
  "/Converters/linkedConversions/PountToOthers": {
    "title": "Pount To Others Converter — Free & Instant",
    "description": "Convert pount to others quickly and accurately with our free online converter."
  },
  "/Converters/linkedConversions/PsiToOthers": {
    "title": "Psi To Others Converter — Free & Instant",
    "description": "Convert psi to others quickly and accurately with our free online converter."
  },
  "/Converters/linkedConversions/QuartToOthers": {
    "title": "Quart To Others Converter — Free & Instant",
    "description": "Convert quart to others quickly and accurately with our free online converter."
  },
  "/Converters/linkedConversions/RadiansToOthers": {
    "title": "Radians To Others Converter — Free & Instant",
    "description": "Convert radians to others quickly and accurately with our free online converter."
  },
  "/Converters/linkedConversions/SecondToOthers": {
    "title": "Second To Others Converter — Free & Instant",
    "description": "Convert second to others quickly and accurately with our free online converter."
  },
  "/Converters/linkedConversions/SquareFootToOthers": {
    "title": "Square Foot To Others Converter — Free & Instant",
    "description": "Convert square foot to others quickly and accurately with our free online converter."
  },
  "/Converters/linkedConversions/SquareMeterToOthers": {
    "title": "Square Meter To Others Converter — Free & Instant",
    "description": "Convert square meter to others quickly and accurately with our free online converter."
  },
  "/Converters/linkedConversions/SquareMilesToOthers": {
    "title": "Square Miles To Others Converter — Free & Instant",
    "description": "Convert square miles to others quickly and accurately with our free online converter."
  },
  "/Converters/linkedConversions/SquareYardToOthers": {
    "title": "Square Yard To Others Converter — Free & Instant",
    "description": "Convert square yard to others quickly and accurately with our free online converter."
  },
  "/Converters/linkedConversions/StoneToOthers": {
    "title": "Stone To Others Converter — Free & Instant",
    "description": "Convert stone to others quickly and accurately with our free online converter."
  },
  "/Converters/linkedConversions/TeaSpoonToOthers": {
    "title": "Tea Spoon To Others Converter — Free & Instant",
    "description": "Convert tea spoon to others quickly and accurately with our free online converter."
  },
  "/Converters/linkedConversions/TonToOthers": {
    "title": "Ton To Others Converter — Free & Instant",
    "description": "Convert ton to others quickly and accurately with our free online converter."
  },
  "/Converters/linkedConversions/WattToOthers": {
    "title": "Watt To Others Converter — Free & Instant",
    "description": "Convert watt to others quickly and accurately with our free online converter."
  },
  "/Converters/linkedConversions/YardsToOthers": {
    "title": "Yards To Others Converter — Free & Instant",
    "description": "Convert yards to others quickly and accurately with our free online converter."
  },
  "/Converters/linkedConversions/YearsToOthers": {
    "title": "Years To Others Converter — Free & Instant",
    "description": "Convert years to others quickly and accurately with our free online converter."
  },
  "/Converters/MagnetismConverters/MagneticFieldStrengthConverter": {
    "title": "Magnetic Field Strength Converter Converter — Free & Instant",
    "description": "Convert magnetic field strength converter quickly and accurately with our free online converter."
  },
  "/Converters/MagnetismConverters/MagneticFluxConverter": {
    "title": "Magnetic Flux Converter Converter — Free & Instant",
    "description": "Convert magnetic flux converter quickly and accurately with our free online converter."
  },
  "/Converters/MagnetismConverters/MagneticFluxDensityConverter": {
    "title": "Magnetic Flux Density Converter Converter — Free & Instant",
    "description": "Convert magnetic flux density converter quickly and accurately with our free online converter."
  },
  "/Converters/MagnetismConverters/MagnetomotiveForceConverter": {
    "title": "Magnetomotive Force Converter Converter — Free & Instant",
    "description": "Convert magnetomotive force converter quickly and accurately with our free online converter."
  },
  "/Converters/NumberUnits/BinaryToDecimal": {
    "title": "Binary To Decimal Converter — Free & Instant",
    "description": "Convert binary to decimal quickly and accurately with our free online converter."
  },
  "/Converters/NumberUnits/BinaryToHex": {
    "title": "Binary To Hex Converter — Free & Instant",
    "description": "Convert binary to hex quickly and accurately with our free online converter."
  },
  "/Converters/NumberUnits/DecimalToBinary": {
    "title": "Decimal To Binary Converter — Free & Instant",
    "description": "Convert decimal to binary quickly and accurately with our free online converter."
  },
  "/Converters/NumberUnits/DecimalToHex": {
    "title": "Decimal To Hex Converter — Free & Instant",
    "description": "Convert decimal to hex quickly and accurately with our free online converter."
  },
  "/Converters/NumberUnits/HexToBinary": {
    "title": "Hex To Binary Converter — Free & Instant",
    "description": "Convert hex to binary quickly and accurately with our free online converter."
  },
  "/Converters/NumberUnits/HexToDecimal": {
    "title": "Hex To Decimal Converter — Free & Instant",
    "description": "Convert hex to decimal quickly and accurately with our free online converter."
  },
  "/Converters/OtherConverters/DataTransferConverter": {
    "title": "Data Transfer Converter Converter — Free & Instant",
    "description": "Convert data transfer converter quickly and accurately with our free online converter."
  },
  "/Converters/OtherConverters/PrefixesConverter": {
    "title": "Prefixes Converter Converter — Free & Instant",
    "description": "Convert prefixes converter quickly and accurately with our free online converter."
  },
  "/Converters/OtherConverters/SoundConverter": {
    "title": "Sound Converter Converter — Free & Instant",
    "description": "Convert sound converter quickly and accurately with our free online converter."
  },
  "/Converters/OtherConverters/TypographyConverter": {
    "title": "Typography Converter Converter — Free & Instant",
    "description": "Convert typography converter quickly and accurately with our free online converter."
  },
  "/Converters/OtherConverters/VolumeLumberConverter": {
    "title": "Volume Lumber Converter Converter — Free & Instant",
    "description": "Convert volume lumber converter quickly and accurately with our free online converter."
  },
  "/Converters/": {
    "title": " Converter — Free & Instant",
    "description": "Convert  quickly and accurately with our free online converter."
  },
  "/Converters/PowerUnits/BTUToTon": {
    "title": "BTUTo Ton Converter — Free & Instant",
    "description": "Convert btuto ton quickly and accurately with our free online converter."
  },
  "/Converters/PowerUnits/HpToWatts": {
    "title": "Hp To Watts Converter — Free & Instant",
    "description": "Convert hp to watts quickly and accurately with our free online converter."
  },
  "/Converters/PowerUnits/TonToBTU": {
    "title": "Ton To BTU Converter — Free & Instant",
    "description": "Convert ton to btu quickly and accurately with our free online converter."
  },
  "/Converters/PowerUnits/WattsToHp": {
    "title": "Watts To Hp Converter — Free & Instant",
    "description": "Convert watts to hp quickly and accurately with our free online converter."
  },
  "/Converters/PressureUnits/BarToPsi": {
    "title": "Bar To Psi Converter — Free & Instant",
    "description": "Convert bar to psi quickly and accurately with our free online converter."
  },
  "/Converters/PressureUnits/KpaToPsi": {
    "title": "Kpa To Psi Converter — Free & Instant",
    "description": "Convert kpa to psi quickly and accurately with our free online converter."
  },
  "/Converters/PressureUnits/PsiToBar": {
    "title": "Psi To Bar Converter — Free & Instant",
    "description": "Convert psi to bar quickly and accurately with our free online converter."
  },
  "/Converters/PressureUnits/PsiToKpa": {
    "title": "Psi To Kpa Converter — Free & Instant",
    "description": "Convert psi to kpa quickly and accurately with our free online converter."
  },
  "/Converters/RadiologyConverters/RadiationAbsorbedDoseConverter": {
    "title": "Radiation Absorbed Dose Converter Converter — Free & Instant",
    "description": "Convert radiation absorbed dose converter quickly and accurately with our free online converter."
  },
  "/Converters/RadiologyConverters/RadiationActivityConverter": {
    "title": "Radiation Activity Converter Converter — Free & Instant",
    "description": "Convert radiation activity converter quickly and accurately with our free online converter."
  },
  "/Converters/RadiologyConverters/RadiationConverter": {
    "title": "Radiation Converter Converter — Free & Instant",
    "description": "Convert radiation converter quickly and accurately with our free online converter."
  },
  "/Converters/RadiologyConverters/RadiationExposureConverter": {
    "title": "Radiation Exposure Converter Converter — Free & Instant",
    "description": "Convert radiation exposure converter quickly and accurately with our free online converter."
  },
  "/Converters/SpeedUnits/FeetPerSecondToMph": {
    "title": "Feet per Second to MPH Converter – Convert ft/s to Miles per Hour | Converthaven"
    "description": "Convert feet per second to mph quickly and accurately with our free online converter."
  },
  "/Converters/SpeedUnits/KnotToMph": {
    "title": "Knot to MPH Converter – Convert Knots to Miles per Hour | Converthaven"
    "description": "Convert knot to mph quickly and accurately with our free online converter."
  },
  "/Converters/SpeedUnits/KphToMetersPerSecond": {
    "title": "KPH to Meters per Second Converter – Convert km/h to m/s | Converthaven"
    "description": "Convert kph to meters per second quickly and accurately with our free online converter."
  },
  "/Converters/SpeedUnits/MetersPerSecondToKph": {
    "title": "Meters per Second to KPH Converter – Convert m/s to km/h | Converthaven"
    "description": "Convert meters per second to kph quickly and accurately with our free online converter."
  },
  "/Converters/SpeedUnits/MetersPerSecondToMilesPerHour": {
    "title": "Meters per Second to MPH Converter – Convert m/s to Miles per Hour | Converthaven",
    "description": "Convert meters per second to miles per hour quickly and accurately with our free online converter."
  },
  "/Converters/SpeedUnits/MilesPerHourToKnot": {
    "title": "MPH to Knot Converter – Convert Miles per Hour to Knots | Converthaven",
    "description": "Convert miles per hour to knot quickly and accurately with our free online converter."
  },
  "/Converters/SpeedUnits/MilesPerHourToMetersPerSecond": {
    "title": "MPH to Meters per Second Converter – Convert Miles per Hour to m/s | Converthaven",
    "description": "Convert miles per hour to meters per second quickly and accurately with our free online converter."
  },
  "/Converters/SpeedUnits/MphToFeetPerSecond": {
    "title": "MPH to Feet per Second Converter – Convert Miles per Hour to ft/s | Converthaven",
    "description": "Convert mph to feet per second quickly and accurately with our free online converter."
  },
  "/Converters/SpeedUnits/MphToKnot": {
    "title": "MPH to Knot Converter – Convert Miles per Hour to Knots | Converthaven",
    "description": "Convert mph to knot quickly and accurately with our free online converter."
  },
  "/Converters/TemperatureUnits/CelsiusToKelvin": {
    "title": "Celsius To Kelvin Converter — Free & Instant",
    "description": "Convert celsius to kelvin quickly and accurately with our free online converter."
  },
  "/Converters/TemperatureUnits/FahrenheitToKelvin": {
    "title": "Fahrenheit To Kelvin Converter — Free & Instant",
    "description": "Convert fahrenheit to kelvin quickly and accurately with our free online converter."
  },
  "/Converters/TemperatureUnits/KelvinToCelsius": {
    "title": "Kelvin To Celsius Converter — Free & Instant",
    "description": "Convert kelvin to celsius quickly and accurately with our free online converter."
  },
  "/Converters/TemperatureUnits/KelvinToFahrenheit": {
    "title": "Kelvin To Fahrenheit Converter — Free & Instant",
    "description": "Convert kelvin to fahrenheit quickly and accurately with our free online converter."
  },
  "/Converters/test123": {
    "title": "test123 Converter — Free & Instant",
    "description": "Convert test123 quickly and accurately with our free online converter."
  },
  "/Converters/TimeUnits/DaysToHours": {
    "title": "Days To Hours Converter — Free & Instant",
    "description": "Convert days to hours quickly and accurately with our free online converter."
  },
  "/Converters/TimeUnits/DaysToMinutes": {
    "title": "Days To Minutes Converter — Free & Instant",
    "description": "Convert days to minutes quickly and accurately with our free online converter."
  },
  "/Converters/TimeUnits/DaysToMonths": {
    "title": "Days To Months Converter — Free & Instant",
    "description": "Convert days to months quickly and accurately with our free online converter."
  },
  "/Converters/TimeUnits/DaysToSeconds": {
    "title": "Days To Seconds Converter — Free & Instant",
    "description": "Convert days to seconds quickly and accurately with our free online converter."
  },
  "/Converters/TimeUnits/DaysToYears": {
    "title": "Days To Years Converter — Free & Instant",
    "description": "Convert days to years quickly and accurately with our free online converter."
  },
  "/Converters/TimeUnits/HoursToDays": {
    "title": "Hours To Days Converter — Free & Instant",
    "description": "Convert hours to days quickly and accurately with our free online converter."
  },
  "/Converters/TimeUnits/HoursToMinutes": {
    "title": "Hours To Minutes Converter — Free & Instant",
    "description": "Convert hours to minutes quickly and accurately with our free online converter."
  },
  "/Converters/TimeUnits/MillisecondsToSeconds": {
    "title": "Milliseconds To Seconds Converter — Free & Instant",
    "description": "Convert milliseconds to seconds quickly and accurately with our free online converter."
  },
  "/Converters/TimeUnits/MinutesToDays": {
    "title": "Minutes To Days Converter — Free & Instant",
    "description": "Convert minutes to days quickly and accurately with our free online converter."
  },
  "/Converters/TimeUnits/MinutesToHours": {
    "title": "Minutes To Hours Converter — Free & Instant",
    "description": "Convert minutes to hours quickly and accurately with our free online converter."
  },
  "/Converters/TimeUnits/MinutesToSeconds": {
    "title": "Minutes To Seconds Converter — Free & Instant",
    "description": "Convert minutes to seconds quickly and accurately with our free online converter."
  },
  "/Converters/TimeUnits/MonthsToDays": {
    "title": "Months To Days Converter — Free & Instant",
    "description": "Convert months to days quickly and accurately with our free online converter."
  },
  "/Converters/TimeUnits/SecondsToDays": {
    "title": "Seconds To Days Converter — Free & Instant",
    "description": "Convert seconds to days quickly and accurately with our free online converter."
  },
  "/Converters/TimeUnits/SecondsToMilliseconds": {
    "title": "Seconds To Milliseconds Converter — Free & Instant",
    "description": "Convert seconds to milliseconds quickly and accurately with our free online converter."
  },
  "/Converters/TimeUnits/SecondsToMinutes": {
    "title": "Seconds To Minutes Converter — Free & Instant",
    "description": "Convert seconds to minutes quickly and accurately with our free online converter."
  },
  "/Converters/TimeUnits/YearsToDays": {
    "title": "Years To Days Converter — Free & Instant",
    "description": "Convert years to days quickly and accurately with our free online converter."
  },
  "/Converters/VolumeUnits/CcToMl": {
    "title": "Cc To Ml Converter — Free & Instant",
    "description": "Convert cc to ml quickly and accurately with our free online converter."
  },
  "/Converters/VolumeUnits/CcToOz": {
    "title": "Cc To Oz Converter — Free & Instant",
    "description": "Convert cc to oz quickly and accurately with our free online converter."
  },
  "/Converters/VolumeUnits/CubicFeetToCubicYards": {
    "title": "Cubic Feet To Cubic Yards Converter — Free & Instant",
    "description": "Convert cubic feet to cubic yards quickly and accurately with our free online converter."
  },
  "/Converters/VolumeUnits/CubicFeetToGallon": {
    "title": "Cubic Feet To Gallon Converter — Free & Instant",
    "description": "Convert cubic feet to gallon quickly and accurately with our free online converter."
  },
  "/Converters/VolumeUnits/CubicInchesToGallons": {
    "title": "Cubic Inches To Gallons Converter — Free & Instant",
    "description": "Convert cubic inches to gallons quickly and accurately with our free online converter."
  },
  "/Converters/VolumeUnits/CubicInchesToLiters": {
    "title": "Cubic Inches To Liters Converter — Free & Instant",
    "description": "Convert cubic inches to liters quickly and accurately with our free online converter."
  },
  "/Converters/VolumeUnits/CubicYardsToCubicFeet": {
    "title": "Cubic Yards To Cubic Feet Converter — Free & Instant",
    "description": "Convert cubic yards to cubic feet quickly and accurately with our free online converter."
  },
  "/Converters/VolumeUnits/CupsToGallon": {
    "title": "Cups To Gallon Converter — Free & Instant",
    "description": "Convert cups to gallon quickly and accurately with our free online converter."
  },
  "/Converters/VolumeUnits/CupsToLiters": {
    "title": "Cups To Liters Converter — Free & Instant",
    "description": "Convert cups to liters quickly and accurately with our free online converter."
  },
  "/Converters/VolumeUnits/CupsToMl": {
    "title": "Cups To Ml Converter — Free & Instant",
    "description": "Convert cups to ml quickly and accurately with our free online converter."
  },
  "/Converters/VolumeUnits/CupsToPints": {
    "title": "Cups To Pints Converter — Free & Instant",
    "description": "Convert cups to pints quickly and accurately with our free online converter."
  },
  "/Converters/VolumeUnits/CupsToQuart": {
    "title": "Cups To Quart Converter — Free & Instant",
    "description": "Convert cups to quart quickly and accurately with our free online converter."
  },
  "/Converters/VolumeUnits/CupsToTablespoons": {
    "title": "Cups To Tablespoons Converter — Free & Instant",
    "description": "Convert cups to tablespoons quickly and accurately with our free online converter."
  },
  "/Converters/VolumeUnits/GallonsToCubicInches": {
    "title": "Gallons To Cubic Inches Converter — Free & Instant",
    "description": "Convert gallons to cubic inches quickly and accurately with our free online converter."
  },
  "/Converters/VolumeUnits/GallonsToCups": {
    "title": "Gallons To Cups Converter — Free & Instant",
    "description": "Convert gallons to cups quickly and accurately with our free online converter."
  },
  "/Converters/VolumeUnits/GallonsToLiters": {
    "title": "Gallons To Liters Converter — Free & Instant",
    "description": "Convert gallons to liters quickly and accurately with our free online converter."
  },
  "/Converters/VolumeUnits/GallonsToPints": {
    "title": "Gallons To Pints Converter — Free & Instant",
    "description": "Convert gallons to pints quickly and accurately with our free online converter."
  },
  "/Converters/VolumeUnits/GallonsToQuarts": {
    "title": "Gallons To Quarts Converter — Free & Instant",
    "description": "Convert gallons to quarts quickly and accurately with our free online converter."
  },
  "/Converters/VolumeUnits/GallonToCubicFeet": {
    "title": "Gallon To Cubic Feet Converter — Free & Instant",
    "description": "Convert gallon to cubic feet quickly and accurately with our free online converter."
  },
  "/Converters/VolumeUnits/GallonToMl": {
    "title": "Gallon To Ml Converter — Free & Instant",
    "description": "Convert gallon to ml quickly and accurately with our free online converter."
  },
  "/Converters/VolumeUnits/LitersToCubicInches": {
    "title": "Liters To Cubic Inches Converter — Free & Instant",
    "description": "Convert liters to cubic inches quickly and accurately with our free online converter."
  },
  "/Converters/VolumeUnits/LitersToCups": {
    "title": "Liters To Cups Converter — Free & Instant",
    "description": "Convert liters to cups quickly and accurately with our free online converter."
  },
  "/Converters/VolumeUnits/LitersToGallons": {
    "title": "Liters To Gallons Converter — Free & Instant",
    "description": "Convert liters to gallons quickly and accurately with our free online converter."
  },
  "/Converters/VolumeUnits/LitersToPints": {
    "title": "Liters To Pints Converter — Free & Instant",
    "description": "Convert liters to pints quickly and accurately with our free online converter."
  },
  "/Converters/VolumeUnits/LitersToQuarts": {
    "title": "Liters To Quarts Converter — Free & Instant",
    "description": "Convert liters to quarts quickly and accurately with our free online converter."
  },
  "/Converters/VolumeUnits/LiterToOunces": {
    "title": "Liter To Ounces Converter — Free & Instant",
    "description": "Convert liter to ounces quickly and accurately with our free online converter."
  },
  "/Converters/VolumeUnits/LToMl": {
    "title": "LTo Ml Converter — Free & Instant",
    "description": "Convert lto ml quickly and accurately with our free online converter."
  },
  "/Converters/VolumeUnits/MlToCc": {
    "title": "Ml To Cc Converter — Free & Instant",
    "description": "Convert ml to cc quickly and accurately with our free online converter."
  },
  "/Converters/VolumeUnits/MlToCups": {
    "title": "Ml To Cups Converter — Free & Instant",
    "description": "Convert ml to cups quickly and accurately with our free online converter."
  },
  "/Converters/VolumeUnits/MlToGallons": {
    "title": "Ml To Gallons Converter — Free & Instant",
    "description": "Convert ml to gallons quickly and accurately with our free online converter."
  },
  "/Converters/VolumeUnits/MlToL": {
    "title": "Ml To L Converter — Free & Instant",
    "description": "Convert ml to l quickly and accurately with our free online converter."
  },
  "/Converters/VolumeUnits/MlToPints": {
    "title": "Ml To Pints Converter — Free & Instant",
    "description": "Convert ml to pints quickly and accurately with our free online converter."
  },
  "/Converters/VolumeUnits/MlToTeaspoon": {
    "title": "Ml To Teaspoon Converter — Free & Instant",
    "description": "Convert ml to teaspoon quickly and accurately with our free online converter."
  },
  "/Converters/VolumeUnits/OuncesToLiters": {
    "title": "Ounces To Liters Converter — Free & Instant",
    "description": "Convert ounces to liters quickly and accurately with our free online converter."
  },
  "/Converters/VolumeUnits/OzToCc": {
    "title": "Oz To Cc Converter — Free & Instant",
    "description": "Convert oz to cc quickly and accurately with our free online converter."
  },
  "/Converters/VolumeUnits/PintsToGallon": {
    "title": "Pints To Gallon Converter — Free & Instant",
    "description": "Convert pints to gallon quickly and accurately with our free online converter."
  },
  "/Converters/VolumeUnits/PintsToLiters": {
    "title": "Pints To Liters Converter — Free & Instant",
    "description": "Convert pints to liters quickly and accurately with our free online converter."
  },
  "/Converters/VolumeUnits/PintToCups": {
    "title": "Pint To Cups Converter — Free & Instant",
    "description": "Convert pint to cups quickly and accurately with our free online converter."
  },
  "/Converters/VolumeUnits/PintToMl": {
    "title": "Pint To Ml Converter — Free & Instant",
    "description": "Convert pint to ml quickly and accurately with our free online converter."
  },
  "/Converters/VolumeUnits/QuartsToCups": {
    "title": "Quarts To Cups Converter — Free & Instant",
    "description": "Convert quarts to cups quickly and accurately with our free online converter."
  },
  "/Converters/VolumeUnits/QuartsToGallon": {
    "title": "Quarts To Gallon Converter — Free & Instant",
    "description": "Convert quarts to gallon quickly and accurately with our free online converter."
  },
  "/Converters/VolumeUnits/QuartsToLiters": {
    "title": "Quarts To Liters Converter — Free & Instant",
    "description": "Convert quarts to liters quickly and accurately with our free online converter."
  },
  "/Converters/VolumeUnits/TablespoonsToCups": {
    "title": "Tablespoons To Cups Converter — Free & Instant",
    "description": "Convert tablespoons to cups quickly and accurately with our free online converter."
  },
  "/Converters/VolumeUnits/TeaspoonToMl": {
    "title": "Teaspoon To Ml Converter — Free & Instant",
    "description": "Convert teaspoon to ml quickly and accurately with our free online converter."
  },
  "/Converters/WeightAndMass/GramsToMilligrams": {
    "title": "Grams To Milligrams Converter — Free & Instant",
    "description": "Convert grams to milligrams quickly and accurately with our free online converter."
  },
  "/Converters/WeightAndMass/GramsToOunces": {
    "title": "Grams To Ounces Converter — Free & Instant",
    "description": "Convert grams to ounces quickly and accurately with our free online converter."
  },
  "/Converters/WeightAndMass/GramsToPounds": {
    "title": "Grams To Pounds Converter — Free & Instant",
    "description": "Convert grams to pounds quickly and accurately with our free online converter."
  },
  "/Converters/WeightAndMass/GramToKg": {
    "title": "Gram To kg Converter — Free & Instant",
    "description": "Convert gram to kg quickly and accurately with our free online converter."
  },
  "/Converters/WeightAndMass/KgToGram": {
    "title": "kg To Gram Converter — Free & Instant",
    "description": "Convert kg to gram quickly and accurately with our free online converter."
  },
  "/Converters/WeightAndMass/KgToLbs": {
    "title": "kg To Lbs Converter — Free & Instant",
    "description": "Convert kg to lbs quickly and accurately with our free online converter."
  },
  "/Converters/WeightAndMass/KgToOz": {
    "title": "kg To Oz Converter — Free & Instant",
    "description": "Convert kg to oz quickly and accurately with our free online converter."
  },
  "/Converters/WeightAndMass/LbsToKg": {
    "title": "Lbs To kg Converter — Free & Instant",
    "description": "Convert lbs to kg quickly and accurately with our free online converter."
  },
  "/Converters/WeightAndMass/LbsToStone": {
    "title": "Lbs To Stone Converter — Free & Instant",
    "description": "Convert lbs to stone quickly and accurately with our free online converter."
  },
  "/Converters/WeightAndMass/LbsToTon": {
    "title": "Lbs To Ton Converter — Free & Instant",
    "description": "Convert lbs to ton quickly and accurately with our free online converter."
  },
  "/Converters/WeightAndMass/MilligramsToGrams": {
    "title": "Milligrams To Grams Converter — Free & Instant",
    "description": "Convert milligrams to grams quickly and accurately with our free online converter."
  },
  "/Converters/WeightAndMass/OuncesToGrams": {
    "title": "Ounces To Grams Converter — Free & Instant",
    "description": "Convert ounces to grams quickly and accurately with our free online converter."
  },
  "/Converters/WeightAndMass/OuncesToPounds": {
    "title": "Ounces To Pounds Converter — Free & Instant",
    "description": "Convert ounces to pounds quickly and accurately with our free online converter."
  },
  "/Converters/WeightAndMass/OzToKg": {
    "title": "Oz To kg Converter — Free & Instant",
    "description": "Convert oz to kg quickly and accurately with our free online converter."
  },
  "/Converters/WeightAndMass/PoundsToGrams": {
    "title": "Pounds To Grams Converter — Free & Instant",
    "description": "Convert pounds to grams quickly and accurately with our free online converter."
  },
  "/Converters/WeightAndMass/PoundsToOunces": {
    "title": "Pounds To Ounces Converter — Free & Instant",
    "description": "Convert pounds to ounces quickly and accurately with our free online converter."
  },
  "/Converters/WeightAndMass/StoneToLbs": {
    "title": "Stone To Lbs Converter — Free & Instant",
    "description": "Convert stone to lbs quickly and accurately with our free online converter."
  },
  "/Converters/WeightAndMass/TonToLbs": {
    "title": "Ton To Lbs Converter — Free & Instant",
    "description": "Convert ton to lbs quickly and accurately with our free online converter."
  }
}
